stytra/__init__.py
stytra/core.py
stytra/utilities.py
stytra/calibration/__init__.py
stytra/collectors/__init__.py
stytra/collectors/accumulators.py
stytra/collectors/data_collector.py
stytra/collectors/namedtuplequeue.py
stytra/examples/__init__.py
stytra/examples/camera_record_exp.py
stytra/examples/closed_loop_exp.py
stytra/examples/combined_conditional_exp.py
stytra/examples/combined_exp.py
stytra/examples/custom_exp.py
stytra/examples/custom_metadata_exp.py
stytra/examples/custom_tracking_exp.py
stytra/examples/custom_trigger_exp.py
stytra/examples/custom_visual_exp.py
stytra/examples/display_camera_exp.py
stytra/examples/display_config_cam.py
stytra/examples/display_opencv_cam.py
stytra/examples/eye_tracking_exp.py
stytra/examples/flash_exp.py
stytra/examples/gratings_exp.py
stytra/examples/imaging_exp.py
stytra/examples/looming_exp.py
stytra/examples/most_basic_exp.py
stytra/examples/moving_bg_coordinates.py
stytra/examples/no_stytra_exp.py
stytra/examples/phototaxis.py
stytra/examples/plot_dynamic_exp.py
stytra/examples/portugues2011_exp.py
stytra/examples/self_calib_cl_exp.py
stytra/examples/serialcomm example.py
stytra/examples/stimulus_trigger_exp.py
stytra/examples/tail_tracking_exp.py
stytra/examples/visual_acuity_exp.py
stytra/examples/windmill_exp.py
stytra/examples/zmq_trigger.py
stytra/examples/zmq_trigger_exp.py
stytra/examples/assets/coordinate_system.png
stytra/examples/assets/fish_compressed.h5
stytra/examples/assets/fish_free_compressed.h5
stytra/experiments/__init__.py
stytra/experiments/camera_recording_experiment.py
stytra/experiments/fish_pipelines.py
stytra/experiments/tracking_experiments.py
stytra/gui/__init__.py
stytra/gui/buttons.py
stytra/gui/camera_display.py
stytra/gui/container_windows.py
stytra/gui/fishplots.py
stytra/gui/framerate_viewer.py
stytra/gui/monitor_control.py
stytra/gui/multiscope.py
stytra/gui/protocol_control.py
stytra/gui/status_display.py
stytra/hardware/__init__.py
stytra/hardware/serial.py
stytra-0.8.34.dist-info/LICENSE.txt
stytra-0.8.34.dist-info/METADATA
stytra-0.8.34.dist-info/WHEEL
stytra-0.8.34.dist-info/top_level.txt
stytra-0.8.34.dist-info/RECORD
