Metadata-Version: 2.1
Name: stytra
Version: 0.8.34
Summary: A modular package to control stimulation and track behavior experiments.
Home-page: UNKNOWN
Author: Vilim Stih, Luigi Petrucco @portugueslab
Author-email: vilim@neuro.mpg.de
License: GPLv3+
Project-URL: Source, https://github.com/portugueslab/stytra
Project-URL: Tracker, https://github.com/portugueslab/stytra/issues
Keywords: tracking behavior experiments
Platform: UNKNOWN
Classifier: Development Status :: 4 - Beta
Classifier: Intended Audience :: Science/Research
Classifier: License :: OSI Approved :: GNU General Public License v3 or later (GPLv3+)
Classifier: Programming Language :: Python :: 3.6
Classifier: Programming Language :: Python :: 3.7
Requires-Dist: pyqtgraph (>=0.10.0)
Requires-Dist: numpy
Requires-Dist: numba
Requires-Dist: pandas
Requires-Dist: qdarkstyle
Requires-Dist: qimage2ndarray
Requires-Dist: flammkuchen
Requires-Dist: anytree
Requires-Dist: pims
Requires-Dist: GitPython
Requires-Dist: colorspacious
Requires-Dist: arrayqueues (>=1.2.0b0)
Requires-Dist: pillow
Requires-Dist: scikit-image
Requires-Dist: imageio
Requires-Dist: imageio-ffmpeg
Requires-Dist: lightparam (>=0.3.7)
